xtgeoviz/__init__.py
xtgeoviz/version.py
xtgeoviz/frontends/__init__.py
xtgeoviz/frontends/_xsectplotting_config.py
xtgeoviz/frontends/_xsectplotting_load.py
xtgeoviz/frontends/_xsectplotting_plotting.py
xtgeoviz/frontends/xsectplotting.py
xtgeoviz/plot/__init__.py
xtgeoviz/plot/_colortables.py
xtgeoviz/plot/_libwrapper.py
xtgeoviz/plot/baseplot.py
xtgeoviz/plot/grid3d_slice.py
xtgeoviz/plot/quickplot.py
xtgeoviz/plot/xsection.py
xtgeoviz/plot/xtmap.py
xtgeoviz-0.3.0.dist-info/licenses/LICENSE
xtgeoviz-0.3.0.dist-info/METADATA
xtgeoviz-0.3.0.dist-info/WHEEL
xtgeoviz-0.3.0.dist-info/top_level.txt
xtgeoviz-0.3.0.dist-info/RECORD
