Metadata-Version: 2.4
Name: xtgeoviz
Version: 0.3.0
Summary: Plotting library for xtgeo objects
Author-email: Equinor <fg_fmu-atlas@equinor.com>
License:                    GNU LESSER GENERAL PUBLIC LICENSE
Project-URL: Homepage, https://github.com/equinor/xtgeoviz
Project-URL: Repository, https://github.com/equinor/xtgeoviz
Project-URL: Documentation, https://github.com/equinor/xtgeoviz
Project-URL: Issues, https://github.com/equinor/xtgeoviz/issues
Keywords: energy,subsurface,reservoir,scientific,engineering,maps,xtgeo
Classifier: Development Status :: 4 - Beta
Classifier: Intended Audience :: Science/Research
Classifier: Intended Audience :: Developers
Classifier: Topic :: Scientific/Engineering
Classifier: Topic :: Scientific/Engineering :: Physics
Classifier: Topic :: Software Development :: Libraries
Classifier: Topic :: Utilities
Classifier: Operating System :: POSIX :: Linux
Classifier: Operating System :: Microsoft :: Windows
Classifier: Operating System :: MacOS
Classifier: Programming Language :: Python :: 3.11
Classifier: Programming Language :: Python :: 3.12
Classifier: Programming Language :: Python :: 3.13
Classifier: Natural Language :: English
Classifier: License :: OSI Approved :: GNU Lesser General Public License v3 (LGPLv3)
Requires-Python: >=3.11
License-File: LICENSE
Requires-Dist: PyYAML
Requires-Dist: matplotlib>=3.3.2
Requires-Dist: numpy
Requires-Dist: scipy>=1.5.3
Requires-Dist: xtgeo
Provides-Extra: tests
Requires-Dist: coverage>=4.1; extra == "tests"
Requires-Dist: mypy; extra == "tests"
Requires-Dist: pylint; extra == "tests"
Requires-Dist: pytest; extra == "tests"
Requires-Dist: pytest-cov; extra == "tests"
Requires-Dist: pytest-mock; extra == "tests"
Requires-Dist: pytest-runner; extra == "tests"
Requires-Dist: pytest-xdist; extra == "tests"
Requires-Dist: rstcheck; extra == "tests"
Requires-Dist: ruff; extra == "tests"
Requires-Dist: types-PyYAML; extra == "tests"
Provides-Extra: docs
Requires-Dist: autoapi; extra == "docs"
Requires-Dist: myst-parser; extra == "docs"
Requires-Dist: sphinx; extra == "docs"
Requires-Dist: sphinx-argparse; extra == "docs"
Requires-Dist: sphinx-autodoc-typehints<2.4; extra == "docs"
Requires-Dist: sphinx-copybutton; extra == "docs"
Requires-Dist: sphinx-togglebutton; extra == "docs"
Requires-Dist: sphinx_rtd_theme; extra == "docs"
Requires-Dist: sphinxcontrib-apidoc; extra == "docs"
Dynamic: license-file
